forklift/__init__.py
forklift/__main__.py
forklift/api.py
forklift/cli.py
forklift/forklift.readme.md
forklift/readers.py
forklift/engine/__init__.py
forklift/engine/exceptions.py
forklift/engine/forklift.engine.readme.md
forklift/engine/forklift_core.py
forklift/engine/config/__init__.py
forklift/engine/config/enums.py
forklift/engine/config/forklift.engine.config.readme.md
forklift/engine/config/import_config.py
forklift/engine/config/processing_results.py
forklift/engine/importers/__init__.py
forklift/engine/importers/excel_importer.py
forklift/engine/importers/forklift.engine.importers.readme.md
forklift/engine/importers/sql_importer.py
forklift/engine/processors/__init__.py
forklift/engine/processors/base.py
forklift/engine/processors/base_processor.py
forklift/engine/processors/batch_converter.py
forklift/engine/processors/batch_processor.py
forklift/engine/processors/csv_processor.py
forklift/engine/processors/forklift.engine.processors.readme.md
forklift/engine/processors/header_detector.py
forklift/engine/processors/schema_processor.py
forklift/engine/processors/validator.py
forklift/inputs/__init__.py
forklift/inputs/config.py
forklift/inputs/csv.py
forklift/inputs/excel.py
forklift/inputs/forklift.inputs.readme.md
forklift/inputs/fwf.py
forklift/inputs/fwf_utils.py
forklift/inputs/sql.py
forklift/inputs/fwf/__init__.py
forklift/inputs/fwf/converters.py
forklift/inputs/fwf/detectors.py
forklift/inputs/fwf/forklift.inputs.fwf
forklift/inputs/fwf/handlers.py
forklift/inputs/fwf/parsers.py
forklift/inputs/fwf/validators.py
forklift/inputs/sql/__init__.py
forklift/inputs/sql/connection.py
forklift/inputs/sql/forklift.inputs.sql.readme.md
forklift/inputs/sql/handler.py
forklift/inputs/sql/reader.py
forklift/inputs/sql/schema.py
forklift/inputs/sql/types.py
forklift/io/__init__.py
forklift/io/forklift.io.readme.md
forklift/io/s3_streaming.py
forklift/io/unified_io.py
forklift/metadata/__init__.py
forklift/metadata/forklift.metadata.readme.md
forklift_etl-0.1.4.dist-info/METADATA
forklift_etl-0.1.4.dist-info/WHEEL
forklift_etl-0.1.4.dist-info/entry_points.txt
forklift_etl-0.1.4.dist-info/licenses/LICENSE
forklift_etl-0.1.4.dist-info/RECORD
