Metadata-Version: 2.4
Name: forklift-etl
Version: 0.1.4
Summary: A powerful data processing and schema generation tool with PyArrow streaming, validation, and S3 support
Project-URL: Homepage, https://github.com/cornyhorse/forklift
Project-URL: Documentation, https://github.com/cornyhorse/forklift/blob/main/docs/
Project-URL: Repository, https://github.com/cornyhorse/forklift
Project-URL: Bug Tracker, https://github.com/cornyhorse/forklift/issues
Project-URL: Changelog, https://github.com/cornyhorse/forklift/blob/main/CHANGELOG.md
Author-email: Matt <matt@mattkingsbury.com>
Maintainer-email: Matt <matt@mattkingsbury.com>
License: MIT License
License-File: LICENSE
Keywords: csv,data-processing,etl,excel,parquet,pyarrow,s3,schema-generation,validation
Classifier: Development Status :: 4 - Beta
Classifier: Intended Audience :: Developers
Classifier: Intended Audience :: Science/Research
Classifier: License :: OSI Approved :: MIT License
Classifier: Operating System :: OS Independent
Classifier: Programming Language :: Python :: 3
Classifier: Programming Language :: Python :: 3.8
Classifier: Programming Language :: Python :: 3.9
Classifier: Programming Language :: Python :: 3.10
Classifier: Programming Language :: Python :: 3.11
Classifier: Programming Language :: Python :: 3.12
Classifier: Topic :: Database
Classifier: Topic :: Scientific/Engineering :: Information Analysis
Classifier: Topic :: Software Development :: Libraries :: Python Modules
Classifier: Topic :: Utilities
Requires-Python: >=3.8
Requires-Dist: boto3>=1.20.0
Requires-Dist: botocore>=1.23.0
Requires-Dist: jsonschema>=4.0.0
Requires-Dist: pandas>=1.3.0
Requires-Dist: pyarrow>=10.0.0
Requires-Dist: python-dateutil>=2.8.0
Requires-Dist: typing-extensions>=4.0.0; python_version < '3.10'
Provides-Extra: all
Requires-Dist: openpyxl>=3.0.0; extra == 'all'
Requires-Dist: polars>=0.18.0; extra == 'all'
Requires-Dist: pyodbc>=4.0.0; extra == 'all'
Requires-Dist: pyperclip>=1.8.0; extra == 'all'
Requires-Dist: pyspark>=3.0.0; extra == 'all'
Provides-Extra: clipboard
Requires-Dist: pyperclip>=1.8.0; extra == 'clipboard'
Provides-Extra: dev
Requires-Dist: black>=22.0.0; extra == 'dev'
Requires-Dist: flake8>=5.0.0; extra == 'dev'
Requires-Dist: mypy>=1.0.0; extra == 'dev'
Requires-Dist: pre-commit>=2.20.0; extra == 'dev'
Requires-Dist: pytest-cov>=4.0.0; extra == 'dev'
Requires-Dist: pytest>=7.0.0; extra == 'dev'
Provides-Extra: excel
Requires-Dist: openpyxl>=3.0.0; extra == 'excel'
Provides-Extra: polars
Requires-Dist: polars>=0.18.0; extra == 'polars'
Provides-Extra: spark
Requires-Dist: pyspark>=3.0.0; extra == 'spark'
Provides-Extra: sql
Requires-Dist: pyodbc>=4.0.0; extra == 'sql'
